<?xml version="1.0" encoding="UTF-8"?>
<configuration>
	<client>
		<properties>
			<property name="foo" value="bar"/>
			<property name="baz" value="biz"/>
		</properties>
		<window name="Phase 3" mode="windowed" width="800" height="800" />
		<maps>
			<map name="map1.tmx"/>
		</maps>
	</client>
	<physics>
		<properties>
			<property name="bar" value="foo"/>
		</properties>
	</physics>
	<networking>
		<properties>
			<property name="bar2" value="foo2"/>
		</properties>
	</networking>
</configuration>